MANIFEST.in
README.rst
setup.cfg
setup.py
wagtailplus/__init__.py
wagtailplus.egg-info/PKG-INFO
wagtailplus.egg-info/SOURCES.txt
wagtailplus.egg-info/dependency_links.txt
wagtailplus.egg-info/not-zip-safe
wagtailplus.egg-info/requires.txt
wagtailplus.egg-info/top_level.txt
wagtailplus/tests/__init__.py
wagtailplus/tests/settings.py
wagtailplus/tests/views.py
wagtailplus/utils/__init__.py
wagtailplus/utils/edit_handlers.py
wagtailplus/utils/views/__init__.py
wagtailplus/utils/views/chooser.py
wagtailplus/utils/views/crud.py
wagtailplus/wagtaillinks/__init__.py
wagtailplus/wagtaillinks/admin_urls.py
wagtailplus/wagtaillinks/apps.py
wagtailplus/wagtaillinks/forms.py
wagtailplus/wagtaillinks/models.py
wagtailplus/wagtaillinks/rich_text.py
wagtailplus/wagtaillinks/wagtail_hooks.py
wagtailplus/wagtaillinks/wagtailadmin_urls.py
wagtailplus/wagtaillinks/migrations/0001_initial.py
wagtailplus/wagtaillinks/migrations/0002_initial_data.py
wagtailplus/wagtaillinks/migrations/__init__.py
wagtailplus/wagtaillinks/static/wagtaillinks/js/hallo-plugins/hallo-wagtaillink.js
wagtailplus/wagtaillinks/templates/wagtaillinks/chooser/chooser.html
wagtailplus/wagtaillinks/templates/wagtaillinks/chooser/chooser.js
wagtailplus/wagtaillinks/templates/wagtaillinks/chooser/chosen.js
wagtailplus/wagtaillinks/templates/wagtaillinks/chooser/link_chosen.js
wagtailplus/wagtaillinks/templates/wagtaillinks/chooser/results.html
wagtailplus/wagtaillinks/templates/wagtaillinks/homepage/site_summary_links.html
wagtailplus/wagtaillinks/templates/wagtaillinks/links/add.html
wagtailplus/wagtaillinks/templates/wagtaillinks/links/confirm_delete.html
wagtailplus/wagtaillinks/templates/wagtaillinks/links/edit.html
wagtailplus/wagtaillinks/templates/wagtaillinks/links/index.html
wagtailplus/wagtaillinks/templates/wagtaillinks/links/list.html
wagtailplus/wagtaillinks/templates/wagtaillinks/links/results.html
wagtailplus/wagtaillinks/tests/__init__.py
wagtailplus/wagtaillinks/tests/test_hooks.py
wagtailplus/wagtaillinks/tests/test_models.py
wagtailplus/wagtaillinks/tests/test_rich_text.py
wagtailplus/wagtaillinks/tests/test_views.py
wagtailplus/wagtaillinks/views/__init__.py
wagtailplus/wagtaillinks/views/chooser.py
