Metadata-Version: 1.1
Name: wagtailplus
Version: 0.3.7
Summary: Modular add-ons for Wagtail CMS
Home-page: https://github.com/rfosterslo/wagtailplus
Author: Ryan Foster
Author-email: rfosterslo@gmail.com
License: UNKNOWN
Download-URL: https://github.com/rfosterslo/wagtailplus/archive/v0.3.7.tar.gz
Keywords: django,wagtail,cms
Platform: UNKNOWN
